photongui/__init__.py
photongui/config.py
photongui/data.py
photongui/util.py
photongui/window.py
photongui/windowBlueprint.py
photongui/api/__init__.py
photongui/api/css.py
photongui/api/js.py
photongui/api/utils/__init__.py
photongui/api/utils/alert.py
photongui/api/utils/drag.py
photongui/api/utils/dragExternalFile.py
photongui/api/utils/loadCssFile.py
photongui/api/utils/loadSnippet.py
photongui/api/utils/py_js_bridge.py
photongui/api/utils/screenCapture.py
photongui/gui/images/icon.png
photongui-1.1.0.dist-info/LICENSE
photongui-1.1.0.dist-info/METADATA
photongui-1.1.0.dist-info/WHEEL
photongui-1.1.0.dist-info/top_level.txt
photongui-1.1.0.dist-info/RECORD
