Metadata-Version: 2.1
Name: photongui
Version: 1.1.0
Summary: Build GUI in Python with JavaScript, HTML, and CSS.
Home-page: https://github.com/Mohamed501258/photongui
Author: Muhammed Bassiouni
Author-email: 
License: MIT
Platform: UNKNOWN
Classifier: License :: OSI Approved :: MIT License
Classifier: Operating System :: OS Independent
Classifier: Programming Language :: Python :: 3
Classifier: Programming Language :: Python :: 3.5
Classifier: Programming Language :: Python :: 3.6
Classifier: Programming Language :: Python :: 3.7
Classifier: Programming Language :: Python :: 3.8
License-File: LICENSE
Requires-Dist: pyobjc-core ; sys_platform == "darwin"
Requires-Dist: pyobjc-framework-Cocoa ; sys_platform == "darwin"
Requires-Dist: pyobjc-framework-WebKit ; sys_platform == "darwin"
